minari/__init__.py
minari/cli.py
minari/namespace.py
minari/serialization.py
minari/utils.py
minari/data_collector/__init__.py
minari/data_collector/data_collector.py
minari/data_collector/episode_buffer.py
minari/data_collector/callbacks/__init__.py
minari/data_collector/callbacks/episode_metadata.py
minari/data_collector/callbacks/step_callback.py
minari/dataset/__init__.py
minari/dataset/episode_data.py
minari/dataset/minari_dataset.py
minari/dataset/minari_storage.py
minari/dataset/step_data.py
minari/dataset/_storages/__init__.py
minari/dataset/_storages/arrow_storage.py
minari/dataset/_storages/hdf5_storage.py
minari/storage/__init__.py
minari/storage/datasets_root_dir.py
minari/storage/hosting.py
minari/storage/local.py
minari/storage/remotes/__init__.py
minari/storage/remotes/cloud_storage.py
minari/storage/remotes/gcp.py
minari/storage/remotes/huggingface.py
minari-0.5.3.dist-info/licenses/LICENSE
minari-0.5.3.dist-info/METADATA
minari-0.5.3.dist-info/WHEEL
minari-0.5.3.dist-info/entry_points.txt
minari-0.5.3.dist-info/top_level.txt
minari-0.5.3.dist-info/RECORD
