Metadata-Version: 2.4
Name: minari
Version: 0.5.3
Summary: A standard format for offline reinforcement learning datasets, with popular reference datasets and related utilities.
Author-email: Farama Foundation <contact@farama.org>
License: MIT License
Project-URL: Homepage, https://farama.org
Project-URL: Repository, https://github.com/Farama-Foundation/Minari
Project-URL: Documentation, https://minari.farama.org/
Project-URL: Bug Report, https://github.com/Farama-Foundation/Minari/issues
Keywords: Reinforcement Learning,Offline RL,RL,AI,Gymnasium,Farama
Classifier: Development Status :: 4 - Beta
Classifier: License :: OSI Approved :: MIT License
Classifier: Programming Language :: Python :: 3
Classifier: Programming Language :: Python :: 3.8
Classifier: Programming Language :: Python :: 3.9
Classifier: Programming Language :: Python :: 3.10
Classifier: Programming Language :: Python :: 3.11
Classifier: Programming Language :: Python :: 3.12
Classifier: Intended Audience :: Science/Research
Classifier: Topic :: Scientific/Engineering :: Artificial Intelligence
Requires-Python: >=3.8
License-File: LICENSE
Requires-Dist: numpy>=1.21.0
Requires-Dist: typing_extensions>=4.4.0
Requires-Dist: typer[all]>=0.9.0
Requires-Dist: gymnasium>=0.28.1
Requires-Dist: packaging
Provides-Extra: arrow
Requires-Dist: pyarrow; extra == "arrow"
Provides-Extra: hdf5
Requires-Dist: h5py>=3.8.0; extra == "hdf5"
Provides-Extra: gcs
Requires-Dist: google-cloud-storage>=2.5.0; extra == "gcs"
Requires-Dist: tqdm; extra == "gcs"
Provides-Extra: hf
Requires-Dist: huggingface_hub; extra == "hf"
Provides-Extra: create
Requires-Dist: jax[cpu]; extra == "create"
Provides-Extra: all
Requires-Dist: minari[arrow,create,gcs,hdf5,hf]; extra == "all"
Provides-Extra: testing
Requires-Dist: pytest>=7.1.3; extra == "testing"
Requires-Dist: gymnasium-robotics>=1.2.3; extra == "testing"
Requires-Dist: mktestdocs; extra == "testing"
Requires-Dist: scikit-image; extra == "testing"
Provides-Extra: integrations
Requires-Dist: torchrl; extra == "integrations"
Requires-Dist: agilerl>=1.0.6; extra == "integrations"
Requires-Dist: d3rlpy; extra == "integrations"
Dynamic: license-file
